nats_app/__init__.py
nats_app/app.py
nats_app/errors.py
nats_app/marshaling.py
nats_app/meta.py
nats_app/middlewares/__init__.py
nats_app/middlewares/common.py
nats_app/middlewares/log.py
nats_app/middlewares/validation.py
nats_app/router.py
nats_app/tasks_queue.py
nats_app/tests/__init__.py
nats_app/tests/conftest.py
nats_app/tests/mock.py
nats_app/tests/test_app.py
nats_app/tests/test_jsm.py
nats_app/tests/test_routes.py
nats_app/tests/test_tasks_queue.py
nats_app-0.7.6.dist-info/METADATA
nats_app-0.7.6.dist-info/WHEEL
nats_app-0.7.6.dist-info/licenses/LICENSE
nats_app-0.7.6.dist-info/RECORD
