Metadata-Version: 2.4
Name: nats-app
Version: 0.7.6
Summary: NATS App is wrapper client on NATS Connection
License: Apache-2.0
License-File: LICENSE
Keywords: nats
Author: Vadym Statishyn
Author-email: statishin@gmail.com
Requires-Python: >=3.12,<4.0
Classifier: Intended Audience :: Developers
Classifier: License :: OSI Approved :: Apache Software License
Classifier: Programming Language :: Python
Classifier: Programming Language :: Python :: 3
Classifier: Programming Language :: Python :: 3.12
Classifier: Programming Language :: Python :: 3.13
Classifier: Programming Language :: Python :: 3.14
Classifier: Programming Language :: Python :: 3.10
Classifier: Programming Language :: Python :: 3.11
Classifier: Programming Language :: Python :: 3.9
Classifier: Topic :: Software Development :: Libraries :: Python Modules
Requires-Dist: fastapi (>=0.115,<0.117)
Requires-Dist: nats-py (>=2.9,<3.0)
Requires-Dist: pydantic (>=2,<3)
Requires-Dist: ujson (>=5.10,<6.0)
